LICENSE
README.md
screenshot.png
setup.py
pretty_csv_diff/__init__.py
pretty_csv_diff/__main__.py
pretty_csv_diff/pretty_csv_diff.py
pretty_csv_diff.egg-info/PKG-INFO
pretty_csv_diff.egg-info/SOURCES.txt
pretty_csv_diff.egg-info/dependency_links.txt
pretty_csv_diff.egg-info/entry_points.txt
pretty_csv_diff.egg-info/top_level.txt