Metadata-Version: 2.1
Name: pretty-csv-diff
Version: 0.1.1
Home-page: https://github.com/eternity8/pretty-csv-diff
License: Apache License 2.0
Classifier: Programming Language :: Python
Classifier: Programming Language :: Python :: 3
Classifier: License :: OSI Approved :: Apache Software License
License-File: LICENSE
